odoo8_addon_crm_rma_advance_warranty-8.0.1.0.0.99.dev16-py3.8-nspkg.pth
odoo_addons/crm_rma_advance_warranty/README.rst
odoo_addons/crm_rma_advance_warranty/__init__.py
odoo_addons/crm_rma_advance_warranty/__openerp__.py
odoo_addons/crm_rma_advance_warranty/i18n/ca.po
odoo_addons/crm_rma_advance_warranty/i18n/crm_rma_advance_warranty.pot
odoo_addons/crm_rma_advance_warranty/i18n/de.po
odoo_addons/crm_rma_advance_warranty/i18n/es.po
odoo_addons/crm_rma_advance_warranty/i18n/es_MX.po
odoo_addons/crm_rma_advance_warranty/i18n/es_PA.po
odoo_addons/crm_rma_advance_warranty/i18n/es_VE.po
odoo_addons/crm_rma_advance_warranty/i18n/eu.po
odoo_addons/crm_rma_advance_warranty/i18n/fi.po
odoo_addons/crm_rma_advance_warranty/i18n/fr.po
odoo_addons/crm_rma_advance_warranty/i18n/it.po
odoo_addons/crm_rma_advance_warranty/i18n/pt_BR.po
odoo_addons/crm_rma_advance_warranty/i18n/pt_PT.po
odoo_addons/crm_rma_advance_warranty/i18n/sl.po
odoo_addons/crm_rma_advance_warranty/i18n/tr_TR.po
odoo_addons/crm_rma_advance_warranty/models/__init__.py
odoo_addons/crm_rma_advance_warranty/models/claim_line.py
odoo_addons/crm_rma_advance_warranty/static/description/icon.png
odoo_addons/crm_rma_advance_warranty/tests/__init__.py
odoo_addons/crm_rma_advance_warranty/tests/test_crm_rma_advance_warranty.py
odoo8_addon_crm_rma_advance_warranty-8.0.1.0.0.99.dev16.dist-info/METADATA
odoo8_addon_crm_rma_advance_warranty-8.0.1.0.0.99.dev16.dist-info/WHEEL
odoo8_addon_crm_rma_advance_warranty-8.0.1.0.0.99.dev16.dist-info/namespace_packages.txt
odoo8_addon_crm_rma_advance_warranty-8.0.1.0.0.99.dev16.dist-info/top_level.txt
odoo8_addon_crm_rma_advance_warranty-8.0.1.0.0.99.dev16.dist-info/RECORD
